my_test_pkg_12345/__init__.py
my_test_pkg_12345_demo-0.0.1.dist-info/METADATA
my_test_pkg_12345_demo-0.0.1.dist-info/WHEEL
my_test_pkg_12345_demo-0.0.1.dist-info/top_level.txt
my_test_pkg_12345_demo-0.0.1.dist-info/RECORD
