Metadata-Version: 2.4
Name: my-test-pkg-12345-demo
Version: 0.0.1
Summary: A harmless test package to demonstrate PyPI publishing
Author: Your Name
Author-email: Your Name <your.email@example.com>
Project-URL: Homepage, https://github.com/yourusername/test
Requires-Python: >=3.6
Dynamic: author
Dynamic: requires-python
